register32.v
module register32(
    input [31:0] ip, 
    input wen, resb,
    output [31:0] op
);

    reg [31:0] register;

    always @(posedge wen or negedge resb) begin
        if (wen == 1) begin
            register = ip;
        end 
        
        if (resb == 0) begin
            register = 0;
        end 

        if (wen == 1 && resb == 0) begin
            register = 32'bz;
        end
    end

    assign op = register;
endmodule

register32tb.v
module register32tb();

    reg [31:0] ip; 
    reg resb;
    wire [31:0] op;
    reg clk;

    register32 uut(
        .ip(ip), .op(op),
        .wen(clk), .resb(resb)
    );

    always begin
        #3; clk = ~clk;
    end

    initial begin
        $dumpfile("register32.vcd");   // Name of output file
        $dumpvars(0, register32tb);

        clk = 0;
        resb = 1;
        #6;
        ip = 32'hFEEDBEEF; 
        #10;
        resb = 0;
        #10;
        resb = 1;
        #10;
        ip = 32'hFEEBDEEF;
        #10;
        $finish;
    end

endmodule

register32.vcd
$date
	Sun Feb 22 00:56:52 2026
$end
$version
	Icarus Verilog
$end
$timescale
	1s
$end
$scope module register32tb $end
$var wire 32 ! op [31:0] $end
$var reg 1 " clk $end
$var reg 32 # ip [31:0] $end
$var reg 1 $ resb $end
$scope module uut $end
$var wire 32 % ip [31:0] $end
$var wire 32 & op [31:0] $end
$var wire 1 $ resb $end
$var wire 1 " wen $end
$var reg 32 ' register [31:0] $end
$upscope $end
$upscope $end
$enddefinitions $end
$comment Show the parameter values. $end
$dumpall
$end
#0
$dumpvars
bx '
bx &
bx %
1$
bx #
0"
bx !
$end
#3
1"
#6
0"
b11111110111011011011111011101111 #
b11111110111011011011111011101111 %
#9
b11111110111011011011111011101111 !
b11111110111011011011111011101111 &
b11111110111011011011111011101111 '
1"
#12
0"
#15
1"
#16
bz !
bz &
bz '
0$
#18
0"
#21
bz !
bz &
bz '
1"
#24
0"
#26
1$
#27
b11111110111011011011111011101111 !
b11111110111011011011111011101111 &
b11111110111011011011111011101111 '
1"
#30
0"
#33
1"
#36
0"
b11111110111010111101111011101111 #
b11111110111010111101111011101111 %
#39
b11111110111010111101111011101111 !
b11111110111010111101111011101111 &
b11111110111010111101111011101111 '
1"
