ROM32.v
module ROM32(
    input [31:0] addr,
    input ce, 
    output [31:0] out
);

    reg [31:0] ROM_ [0:31];

    // Program 
    initial begin
        ROM_[0] = 32'hFEEDBEEF;
        ROM_[1] = 32'hDEEFFFEB;
        ROM_[2] = 32'hABACADAB;
        ROM_[3] = 32'hFEEDBEEF;
        ROM_[4] = 32'hDEEFFFEB;
        ROM_[5] = 32'hABACADAB;
        ROM_[6] = 32'hFEEDBEEF;
        ROM_[7] = 32'hDEEFFFEB;
        ROM_[8] = 32'hABACADAB;
        ROM_[9] = 32'hDEEFFFEB;
        ROM_[10] = 32'hABACADAB;
    end

    reg [31:0] out_;

    always @(addr) begin
        if (ce == 1) begin
            out_ = ROM_[addr];
        end else begin out_ = 32'hzzzzzzzz; end
    end

    assign out = out_;

endmodule

ROM32tb.v
module ROM32tb();

    reg [31:0] addr;
    reg ce;
    wire [31:0] out;

    ROM32 uut(
        .addr(addr), .ce(ce),
        .out(out)
    );

    initial begin
        $dumpfile("ROM32.vcd");   // Name of output file
        $dumpvars(0, ROM32tb);

        ce = 1;

        addr = 0; #1;
        addr = 1; #1;
        addr = 2; #1;
        addr = 3; #1;
        addr = 4; #1;

        ce = 0; #3;
        addr = 5; #1;
        ce = 1; #3;

        addr = 6; #1;
        addr = 7; #1;
        addr = 8; #1;
        addr = 9; #1;
        addr = 10; #1;

        $finish;
    end

endmodule

ROM32.vcd
$date
	Sun Feb 22 19:24:26 2026
$end
$version
	Icarus Verilog
$end
$timescale
	1s
$end
$scope module ROM32tb $end
$var wire 32 ! out [31:0] $end
$var reg 32 " addr [31:0] $end
$var reg 1 # ce $end
$scope module uut $end
$var wire 32 $ addr [31:0] $end
$var wire 1 # ce $end
$var wire 32 % out [31:0] $end
$var reg 32 & out_ [31:0] $end
$upscope $end
$upscope $end
$enddefinitions $end
$comment Show the parameter values. $end
$dumpall
$end
#0
$dumpvars
b11111110111011011011111011101111 &
b11111110111011011011111011101111 %
b0 $
1#
b0 "
b11111110111011011011111011101111 !
$end
#1
b11011110111011111111111111101011 !
b11011110111011111111111111101011 %
b11011110111011111111111111101011 &
b1 "
b1 $
#2
b10101011101011001010110110101011 !
b10101011101011001010110110101011 %
b10101011101011001010110110101011 &
b10 "
b10 $
#3
b11111110111011011011111011101111 !
b11111110111011011011111011101111 %
b11111110111011011011111011101111 &
b11 "
b11 $
#4
b11011110111011111111111111101011 !
b11011110111011111111111111101011 %
b11011110111011111111111111101011 &
b100 "
b100 $
#5
0#
#8
bz !
bz %
bz &
b101 "
b101 $
#9
1#
#12
b11111110111011011011111011101111 !
b11111110111011011011111011101111 %
b11111110111011011011111011101111 &
b110 "
b110 $
#13
b11011110111011111111111111101011 !
b11011110111011111111111111101011 %
b11011110111011111111111111101011 &
b111 "
b111 $
#14
b10101011101011001010110110101011 !
b10101011101011001010110110101011 %
b10101011101011001010110110101011 &
b1000 "
b1000 $
#15
b11011110111011111111111111101011 !
b11011110111011111111111111101011 %
b11011110111011111111111111101011 &
b1001 "
b1001 $
#16
b10101011101011001010110110101011 !
b10101011101011001010110110101011 %
b10101011101011001010110110101011 &
b1010 "
b1010 $
