src/RAM32.v
module RAM32(
  input [31:0] addr, dataIn,
  input clk, writeEnable, enable,
  output [31:0] dataOut
);

  reg [31:0] memory[31:0];

  integer i;

  initial begin
    for (i = 0; i < 31; i = i + 1) begin
      memory[i] = 32'h00000000;
    end
  end

  always @(posedge clk) begin
    if ((writeEnable == 1) && (addr < 31)) begin
      memory[addr] = dataIn;
    end
  end
  
  // We assign 0 to any address that is above 31 because we cannot have actual
  // data that spans to that width of memory 9about 16 GB, cannot simulate)
  // hence we assume its just 0 instead of high impedance
  assign dataOut = ((addr < 31) && (enable == 1)) ? memory[addr] : 32'h00000000;

endmodule

src/alu32.v
module alu32(
	input [31:0] A, B,		// Inputs
	input [1:0] Ctrl,			// For now only four operations supported
	output [31:0] Out,		// Operation result
	output zflg, ovflg, brwflg, negflg // Output characteristic flags
);

	reg [31:0] Out_;		// Operation result
	reg zflg_, ovflg_, brwflg_, negflg_; // Output characteristic flags

  initial begin
    zflg_ = 0;
    ovflg_ = 0;
    brwflg_ = 0;
    negflg_ = 0;
  end

	always @(*) begin
		case (Ctrl)
			// OR reg3, reg1, reg2 -> A = reg1, B = reg2
      // BITWISE LOGICAL OR operation
			4'b00: begin
				Out_ = A | B;
			end
			// SUBI reg4, reg5, 21 -> A = reg5, B = 21
      // SUBTRACT operation
			4'b01: begin
				Out_  = A - B;
			end
			// SW reg6, 5 (reg7) -> ???
      // ADD operation
			4'b10: begin
				Out_ = A + B;	// Setting to 0 for now
			end
			// BEQ reg9, reg8, 7 -> ???
      // WHAT OPERATION????
			4'b11:begin
				Out_ = 0; // Setting to 0 for now
			end
		endcase

		// Check for zero
		if (Out_ == 0) begin
			zflg_ = 1;
		end else begin zflg_ = 0; end
		// Check for negative result
		if (Out_[31] == 1) begin
			negflg_ = 1;
		end else begin negflg_ = 0; end
		// Check if borrow was required
		if (A < B) begin
			brwflg_ = 1;
		end
		// Check if overflow was there -> Not required right now
		ovflg_ = 0;
	end

	// Assign all reg's outputs
	assign Out = Out_;
	assign zflg = zflg_;
	assign ovflg = ovflg_;
	assign negflg = negflg_;
	assign brwflg = brwflg_;

endmodule

src/signextender16_32.v
module signextender16_32(
  input [15:0] inp,
  output [31:0] op
);

  reg [31:0] out_;

  initial begin
    out_ = 32'h00000000;
  end

  always @(*) begin
    out_ = {(inp[15] == 0) ? 16'h0000 : 16'hFFFF, inp};
  end

  assign op = out_;

endmodule

src/registerFile32x9.v
module registerFile32x9(
    input [3:0] readAddr1, readAddr2, writeAddr,
    input [31:0] writeData,
    input writeEnable, resetb, clk,
    output [31:0] readData1, readData2
);

    reg [31:0] registers [8:0];

    integer i;
    initial begin
        for(i = 0; i < 9; i = i + 1) begin
            registers[i] = 0;
        end
    end

    always @(posedge clk) begin
        if ((writeAddr < 9) && (writeEnable == 1)) begin
            registers[writeAddr] = writeData;
        end 
    end

    integer j;
    always @(negedge resetb) begin
        for (j = 0; j < 9; j = j + 1) begin
            registers[j] = 0;
        end
    end

    assign readData1 = (readAddr1 < 9) ? registers[readAddr1] : 32'hxxxxxxxx;
    assign readData2 = (readAddr2 < 9) ? registers[readAddr2] : 32'hxxxxxxxx;

endmodule

src/MUX2x1_32.v
module MUX2x1_32(
  input select,
  input [31:0] inp0, inp1,
  output [31:0] out
);

  reg [31:0] out_;

  always @(*) begin
    if (select == 0) begin
      out_ = inp0;
    end else begin
      out_ = inp1; 
    end
  end

  assign out = out_;

endmodule

src/cu.v
module cu (
    input  [31:0] instr,
    output [1:0] aluCtrl,
    output [3:0] regFileReadAddr1, regFileReadAddr2, regFileWriteAddr,
    output aluSrc, regFileWriteEnable, RAMWriteEnable,
    aluOut_dataMemOut_select, RAMEnable
);

  reg [1:0] aluCtrl_;
  reg regFileWriteEnable_, RAMWriteEnable_;
  reg [3:0] regFileWriteAddr_;
  reg [3:0] regFileReadAddr1_, regFileReadAddr2_;
  reg aluSrc_, aluOut_dataMemOut_select_, RAMEnable_;

  // OR outreg3, inreg1, inreg2 -> R-type
  // SUBI outreg4, inreg5, immval21 -> I-type
  // SW reg6, 5 (reg7) -> I-type (NOT IMPLEMENTED)
  // BEQ reg9, reg8, 7 -> J-type (NOT IMPLEMENTED)
  always @(*) begin
    casez (instr[31:26])
      // R-type (only OR)
      // 000000 5'b<Rd> 5'b<Rs> 5'b<Rt> 5'b<shamt> 6'b<funct>
      6'b000000: begin
        // Only OR as R-type supported as of now hence we set undef
        aluCtrl_ = 2'b00;
        regFileWriteAddr_ = instr[25:21];
        regFileWriteEnable_ = 1;
        regFileReadAddr1_ = instr[20:16];
        regFileReadAddr2_ = instr[15:11];
        aluSrc_ = 0;
        aluOut_dataMemOut_select_ = 0;
        RAMEnable_ = 0;
        RAMWriteEnable_ = 0;
      end
      // I-type
      // 000001 5'b<Rd> 5'b<rS> 16'b<ImmVal>
      6'b000001: begin
        aluCtrl_ = 2'b01;
        regFileWriteAddr_ = instr[25:21];
        regFileWriteEnable_ = 1;
        regFileReadAddr1_ = instr[20:16];
        regFileReadAddr2_ = 5'bzzzzz;
        aluSrc_ = 1;
        aluOut_dataMemOut_select_ = 0;
        RAMEnable_ = 0;
        RAMWriteEnable_ = 0;
      end

      // SW destReg, <ImmVal>(srcAddrReg)
      // I-type 
      // 000010 5'b<Rd> 5'b<Rs> 16'b<ImmVal>
      // ALU needs to do an ADD operation
      6'b000010: begin
        // aluCtrl_ = ??? WE NEED AN ADD OR A SUBTRACT
        aluCtrl_ = 2'b10;
        regFileWriteEnable_ = 1;
        regFileWriteAddr_ = instr[25:21];
        regFileReadAddr1_ = instr[20:16];
        regFileReadAddr2_ = 5'bzzzzz;
        aluSrc_ = 1;
        RAMWriteEnable_ = 0; 
        aluOut_dataMemOut_select_ = 1;
        RAMEnable_ = 1;
        RAMWriteEnable_ = 0;
      end

      default: begin
        aluCtrl_ = 2'bxx;
        regFileWriteAddr_ = 5'bxxxxx;
        regFileWriteEnable_ = 1'bx;
        regFileReadAddr1_ = 5'bxxxxx;
        regFileReadAddr2_ = 5'bxxxxx;
        aluSrc_ = 1'bx;
      end
    endcase
  end

  assign aluCtrl = aluCtrl_;
  assign regFileWriteAddr = regFileWriteAddr_;
  assign regFileWriteEnable = regFileWriteEnable_;
  assign regFileReadAddr1 = regFileReadAddr1_;
  assign regFileReadAddr2 = regFileReadAddr2_;
  assign aluSrc = aluSrc_;
  assign RAMWriteEnable = RAMWriteEnable_;
  assign aluOut_dataMemOut_select = aluOut_dataMemOut_select_;
  assign RAMEnable = RAMEnable_;

endmodule

src/ROM32.v
module ROM32(
    input [31:0] addr,
    input ce, 
    output [31:0] out
);

    reg [31:0] ROM_ [0:31];

    integer i;

    // Program 
    initial begin

        for (i = 0; i < 32; i = i + 1) begin
          ROM_[i]  = 32'h00000000;
        end

        // OR $1, $2, $3 => $1 = $2 | $3;
        ROM_[0] = 32'b00000000001000100001100000000000;
        // SUBI $1, $2, 21 => $1 = $2 - 21;
        ROM_[1] = 32'h04220015;
        // SUBI $2, $1, 0xFFFFFFEA => $1 = $2 - 0xFFFFFFEA; -> Answer will be 1
        ROM_[2] = 32'b00000100010000101111111111101010;
        // SW $6, 10($1) -> Load dataMem from Addr[<$1> + 10] into $6
        ROM_[3] = 32'b00001000110000010000000000000000;
        // OR $3, $1, $6 => $3 = $1 | $6
        ROM_[4] = 32'b00000000011000010011000000000000;
    end

    reg [31:0] out_;

    always @(*) begin
      if (ce == 1) begin
        out_ = (addr < 11) ? ROM_[addr] : 32'hx;
      end
    end

    assign out = out_;

endmodule

register32.v
module register32(
    input [31:0] ip, 
    input wen, resb,
    output [31:0] op
);

    reg [31:0] register;

    always @(posedge wen or negedge resb) begin
        if (wen == 1) begin
            register = ip;
        end 
        
        if (resb == 0) begin
            register = 0;
        end 

        if (wen == 1 && resb == 0) begin
            register = 32'bz;
        end
    end

    assign op = register;
endmodule

src/add32.v
module add32(
    input [31:0] A, B,
    input Cin,
    output [31:0] Sum,
    output Cout
); 

    reg [31:0] _Sum_;
    reg _Cout_;

    always @(*) begin
        {_Cout_, _Sum_} = A + B + Cin;
    end

    assign Sum = _Sum_;
    assign Cout = _Cout_;

endmodule

src/Proc.v
module Proc (
    input reset
);

    // CLOCK SETUP
    reg clk;
    initial clk = 0;
    always begin #1; clk = ~clk; end

    // ALL COMPONENT WIRES
    // For Program Counter PC
    wire [31:0] pcIp, pcOp;
    wire pcWen, pcResb, pcCout;

    // For Instruction Memory
    wire [31:0] instr_;

    // For dataMemory
    wire [31:0] dataMemoryOut_;

    // For Control Unit CU
    wire [1:0] aluCtrl_;
    wire [3:0] regFileReadAddr1_, regFileReadAddr2_, regFileWriteAddr_;
    wire aluSrc_, regFileWriteEnable_, RAMWriteEnable_, 
      aluOut_dataMemOut_select, RAMEnable_;

    // For arithmetic logic unit ALU
	  wire [31:0] aluOut_;		// Operation result
	  wire zflg, ovflg, brwflg, negflg; // Output characteristic flags

    // For register file REGISTERFILE
    wire [31:0] regFileReadData1_, regFileReadData2_;

    // For mux to choose between ALU output and DATAMEMORY output
    wire [31:0] alu_dataMem_MUXOut_;

    // For sign-extender SIGNEXTEND16_32
    wire [31:0] aluImmVal;





    // Some initialization before declaring units
    assign pcResb = reset;  // Assign reet to input for testbench purposes
    assign pcWen = clk;     // Assign pcWriteEnableSignal to clk




    // MODULE DECLARATIONS
    // Adder for the program counter
    add32 pcAdder(
        .A(pcOp), .B(32'h00000004), .Cin(1'b0),
        .Sum(pcIp), .Cout(pcCout)
    );

    register32 PC(
        .ip(pcIp), .wen(pcWen), .resb(pcResb),
        .op(pcOp)
    );

    ROM32 instrMem(
      .addr(pcOp >> 2), .ce(clk), .out(instr_)
    );

    cu CU(
      .instr(instr_),
      .aluCtrl(aluCtrl_),
      .regFileWriteAddr(regFileWriteAddr_),
      .regFileWriteEnable(regFileWriteEnable_),
      .regFileReadAddr1(regFileReadAddr1_), .regFileReadAddr2(regFileReadAddr2_),
      .aluSrc(aluSrc_), .RAMWriteEnable(RAMWriteEnable_), 
      .aluOut_dataMemOut_select(aluOut_dataMemOut_select),
      .RAMEnable(RAMEnable_)
    );

    MUX2x1_32 ALU_DATAMEM_MUX(
      .select(aluOut_dataMemOut_select),
      .inp0(aluOut_), .inp1(dataMemoryOut_),
      .out(alu_dataMem_MUXOut_)
    );

    registerFile32x9 REGISTERFILE(
      .readAddr1(regFileReadAddr1_), 
      .readAddr2(regFileReadAddr2_),
      .writeAddr(regFileWriteAddr_),
      .writeData(alu_dataMem_MUXOut_),
      .writeEnable(regFileWriteEnable_),
      .resetb(1'b1),
      .readData1(regFileReadData1_),
      .readData2(regFileReadData2_),
      .clk(clk)
    );

    signextender16_32 SIGNEXTEND16_32(
      .inp(instr_[15:0]), .op(aluImmVal)
    );

    alu32 ALU(
      .A(regFileReadData1_), 
      .B((aluSrc_ == 1) ? aluImmVal : regFileReadData2_), 
      .Ctrl(aluCtrl_),
      .Out(aluOut_), 
      .zflg(zflg), 
      .ovflg(ovflg), 
      .brwflg(brwflg), 
      .negflg(negflg)
    );

    RAM32 DATAMEMORY(
      .addr(aluOut_), .dataIn(regFileReadData2_),
      .clk(clk), .writeEnable(RAMWriteEnable_),
      .dataOut(dataMemoryOut_), .enable(RAMEnable_)
    );

endmodule

tb/Proctb.v
module Proctb();

    reg reset;

    Proc uut(
        .reset(reset)
    );

    initial begin
        $dumpfile("build/Proctb.vcd");
        $dumpvars(0, Proctb);
        reset = 0;   // reset active
        #2; reset = 1; // release reset
        #100;
        $finish;
    end

endmodule

build/Proctb.vcd
$date
	Wed Mar  4 21:22:01 2026
$end
$version
	Icarus Verilog
$end
$timescale
	1s
$end
$scope module Proctb $end
$var reg 1 ! reset $end
$scope module uut $end
$var wire 1 " pcResb $end
$var wire 1 # pcWen $end
$var wire 1 ! reset $end
$var wire 1 $ zflg $end
$var wire 1 % regFileWriteEnable_ $end
$var wire 4 & regFileWriteAddr_ [3:0] $end
$var wire 32 ' regFileReadData2_ [31:0] $end
$var wire 32 ( regFileReadData1_ [31:0] $end
$var wire 4 ) regFileReadAddr2_ [3:0] $end
$var wire 4 * regFileReadAddr1_ [3:0] $end
$var wire 32 + pcOp [31:0] $end
$var wire 32 , pcIp [31:0] $end
$var wire 1 - pcCout $end
$var wire 1 . ovflg $end
$var wire 1 / negflg $end
$var wire 32 0 instr_ [31:0] $end
$var wire 32 1 dataMemoryOut_ [31:0] $end
$var wire 1 2 brwflg $end
$var wire 32 3 alu_dataMem_MUXOut_ [31:0] $end
$var wire 1 4 aluSrc_ $end
$var wire 1 5 aluOut_dataMemOut_select $end
$var wire 32 6 aluOut_ [31:0] $end
$var wire 32 7 aluImmVal [31:0] $end
$var wire 2 8 aluCtrl_ [1:0] $end
$var wire 1 9 RAMWriteEnable_ $end
$var wire 1 : RAMEnable_ $end
$var reg 1 ; clk $end
$scope module ALU $end
$var wire 32 < B [31:0] $end
$var wire 1 2 brwflg $end
$var wire 1 / negflg $end
$var wire 1 . ovflg $end
$var wire 1 $ zflg $end
$var wire 32 = Out [31:0] $end
$var wire 2 > Ctrl [1:0] $end
$var wire 32 ? A [31:0] $end
$var reg 32 @ Out_ [31:0] $end
$var reg 1 A brwflg_ $end
$var reg 1 B negflg_ $end
$var reg 1 C ovflg_ $end
$var reg 1 D zflg_ $end
$upscope $end
$scope module ALU_DATAMEM_MUX $end
$var wire 32 E inp0 [31:0] $end
$var wire 32 F out [31:0] $end
$var wire 1 5 select $end
$var wire 32 G inp1 [31:0] $end
$var reg 32 H out_ [31:0] $end
$upscope $end
$scope module CU $end
$var wire 1 9 RAMWriteEnable $end
$var wire 2 I aluCtrl [1:0] $end
$var wire 1 5 aluOut_dataMemOut_select $end
$var wire 4 J regFileWriteAddr [3:0] $end
$var wire 1 % regFileWriteEnable $end
$var wire 4 K regFileReadAddr2 [3:0] $end
$var wire 4 L regFileReadAddr1 [3:0] $end
$var wire 32 M instr [31:0] $end
$var wire 1 4 aluSrc $end
$var wire 1 : RAMEnable $end
$var reg 1 : RAMEnable_ $end
$var reg 1 N RAMWriteEnable_ $end
$var reg 2 O aluCtrl_ [1:0] $end
$var reg 1 P aluOut_dataMemOut_select_ $end
$var reg 1 4 aluSrc_ $end
$var reg 4 Q regFileReadAddr1_ [3:0] $end
$var reg 4 R regFileReadAddr2_ [3:0] $end
$var reg 4 S regFileWriteAddr_ [3:0] $end
$var reg 1 T regFileWriteEnable_ $end
$upscope $end
$scope module DATAMEMORY $end
$var wire 32 U addr [31:0] $end
$var wire 1 ; clk $end
$var wire 1 : enable $end
$var wire 1 9 writeEnable $end
$var wire 32 V dataOut [31:0] $end
$var wire 32 W dataIn [31:0] $end
$var integer 32 X i [31:0] $end
$upscope $end
$scope module PC $end
$var wire 1 " resb $end
$var wire 1 # wen $end
$var wire 32 Y op [31:0] $end
$var wire 32 Z ip [31:0] $end
$var reg 32 [ register [31:0] $end
$upscope $end
$scope module REGISTERFILE $end
$var wire 1 ; clk $end
$var wire 4 \ readAddr1 [3:0] $end
$var wire 4 ] readAddr2 [3:0] $end
$var wire 1 ^ resetb $end
$var wire 4 _ writeAddr [3:0] $end
$var wire 32 ` writeData [31:0] $end
$var wire 1 % writeEnable $end
$var wire 32 a readData2 [31:0] $end
$var wire 32 b readData1 [31:0] $end
$var integer 32 c i [31:0] $end
$var integer 32 d j [31:0] $end
$upscope $end
$scope module SIGNEXTEND16_32 $end
$var wire 16 e inp [15:0] $end
$var wire 32 f op [31:0] $end
$var reg 32 g out_ [31:0] $end
$upscope $end
$scope module instrMem $end
$var wire 32 h addr [31:0] $end
$var wire 1 ; ce $end
$var wire 32 i out [31:0] $end
$var reg 32 j out_ [31:0] $end
$var integer 32 k i [31:0] $end
$upscope $end
$scope module pcAdder $end
$var wire 32 l A [31:0] $end
$var wire 32 m B [31:0] $end
$var wire 1 n Cin $end
$var wire 1 - Cout $end
$var wire 32 o Sum [31:0] $end
$var reg 1 p _Cout_ $end
$var reg 32 q _Sum_ [31:0] $end
$upscope $end
$upscope $end
$upscope $end
$enddefinitions $end
$comment Show the parameter values. $end
$dumpall
$end
#0
$dumpvars
b100 q
0p
b100 o
0n
b100 m
b0 l
b100000 k
bx j
bx i
b0 h
b0 g
b0 f
bx e
bx d
b1001 c
bx b
bx a
bx `
bx _
1^
bx ]
bx \
b0 [
b100 Z
b0 Y
b11111 X
bx W
bx V
bx U
xT
bx S
bx R
bx Q
xP
bx O
xN
bx M
bx L
bx K
bx J
bx I
bx H
bx G
bx F
bx E
0D
0C
0B
0A
bx @
bx ?
bx >
bx =
bx <
0;
x:
x9
bx 8
b0 7
bx 6
x5
x4
bx 3
02
bx 1
bx 0
0/
0.
0-
b100 ,
b0 +
bx *
bx )
bx (
bx '
bx &
x%
0$
0#
0"
0!
$end
#1
b0 3
b0 F
b0 `
b0 H
b0 1
b0 G
b0 V
1$
1D
b0 6
b0 =
b0 @
b0 E
b0 U
b1100000000000 7
b1100000000000 f
b1100000000000 g
b0 <
b0 '
b0 W
b0 a
b0 (
b0 ?
b0 b
b1100000000000 e
09
0N
0:
05
0P
04
b11 )
b11 K
b11 R
b11 ]
b10 *
b10 L
b10 Q
b10 \
1%
1T
b1 &
b1 J
b1 _
b1 S
b0 8
b0 >
b0 I
b0 O
b1000100001100000000000 0
b1000100001100000000000 M
b1000100001100000000000 i
b1000100001100000000000 j
1#
1;
#2
0#
0;
1"
1!
#3
b11111111111111111111111111101011 3
b11111111111111111111111111101011 F
b11111111111111111111111111101011 `
b11111111111111111111111111101011 H
12
1A
1/
1B
0$
0D
b11111111111111111111111111101011 6
b11111111111111111111111111101011 =
b11111111111111111111111111101011 @
b11111111111111111111111111101011 E
b11111111111111111111111111101011 U
b10101 7
b10101 f
b10101 g
b10101 <
bx '
bx W
bx a
b10101 e
14
bz )
bz K
bz R
bz ]
b1 8
b1 >
b1 I
b1 O
b100001000100000000000010101 0
b100001000100000000000010101 M
b100001000100000000000010101 i
b100001000100000000000010101 j
b1 h
b1000 ,
b1000 Z
b1000 o
b1000 q
b100 +
b100 Y
b100 [
b100 l
1#
1;
#4
0#
0;
#5
b10110 3
b10110 F
b10110 `
b10110 H
0/
0B
b10110 6
b10110 =
b10110 @
b10110 E
b10110 U
b11111111111111111111111111101010 <
b11111111111111111111111111101010 7
b11111111111111111111111111101010 f
b11111111111111111111111111101010 g
b1111111111101010 e
b10 &
b10 J
b10 _
b10 S
b100010000101111111111101010 0
b100010000101111111111101010 M
b100010000101111111111101010 i
b100010000101111111111101010 j
b10 h
b1100 ,
b1100 Z
b1100 o
b1100 q
b1000 +
b1000 Y
b1000 [
b1000 l
1#
1;
#6
0#
0;
#7
b0 <
b0 1
b0 G
b0 V
1/
1B
b0 7
b0 f
b0 g
0$
0D
b0 e
1:
15
1P
b1 *
b1 L
b1 Q
b1 \
b110 &
b110 J
b110 _
b110 S
b10 8
b10 >
b10 I
b10 O
b1000110000010000000000000000 0
b1000110000010000000000000000 M
b1000110000010000000000000000 i
b1000110000010000000000000000 j
b11 h
b10000 ,
b10000 Z
b10000 o
b10000 q
b1100 +
b1100 Y
b1100 [
b1100 l
b0 3
b0 F
b0 `
b0 H
b11111111111111111111111111101011 6
b11111111111111111111111111101011 =
b11111111111111111111111111101011 @
b11111111111111111111111111101011 E
b11111111111111111111111111101011 U
b11111111111111111111111111101011 (
b11111111111111111111111111101011 ?
b11111111111111111111111111101011 b
1#
1;
#8
0#
0;
#9
b11000000000000 7
b11000000000000 f
b11000000000000 g
b11111111111111111111111111101011 3
b11111111111111111111111111101011 F
b11111111111111111111111111101011 `
b11111111111111111111111111101011 H
b0 '
b0 W
b0 a
b11000000000000 e
0:
05
0P
04
b110 )
b110 K
b110 R
b110 ]
b11 &
b11 J
b11 _
b11 S
b0 8
b0 >
b0 I
b0 O
b11000010011000000000000 0
b11000010011000000000000 M
b11000010011000000000000 i
b11000010011000000000000 j
b100 h
b10100 ,
b10100 Z
b10100 o
b10100 q
b10000 +
b10000 Y
b10000 [
b10000 l
1#
1;
#10
0#
0;
#11
b0 3
b0 F
b0 `
b0 H
0/
0B
1$
1D
b0 6
b0 =
b0 @
b0 E
b0 U
b0 7
b0 f
b0 g
b0 (
b0 ?
b0 b
b0 e
b0 )
b0 K
b0 R
b0 ]
b0 *
b0 L
b0 Q
b0 \
b0 &
b0 J
b0 _
b0 S
b0 0
b0 M
b0 i
b0 j
b101 h
b11000 ,
b11000 Z
b11000 o
b11000 q
b10100 +
b10100 Y
b10100 [
b10100 l
1#
1;
#12
0#
0;
#13
b110 h
b11100 ,
b11100 Z
b11100 o
b11100 q
b11000 +
b11000 Y
b11000 [
b11000 l
1#
1;
#14
0#
0;
#15
b111 h
b100000 ,
b100000 Z
b100000 o
b100000 q
b11100 +
b11100 Y
b11100 [
b11100 l
1#
1;
#16
0#
0;
#17
b1000 h
b100100 ,
b100100 Z
b100100 o
b100100 q
b100000 +
b100000 Y
b100000 [
b100000 l
1#
1;
#18
0#
0;
#19
b1001 h
b101000 ,
b101000 Z
b101000 o
b101000 q
b100100 +
b100100 Y
b100100 [
b100100 l
1#
1;
#20
0#
0;
#21
b1010 h
b101100 ,
b101100 Z
b101100 o
b101100 q
b101000 +
b101000 Y
b101000 [
b101000 l
1#
1;
#22
0#
0;
#23
bx 7
bx f
bx g
bx <
bx '
bx W
bx a
bx (
bx ?
bx b
bx e
x4
bx )
bx K
bx R
bx ]
bx *
bx L
bx Q
bx \
x%
xT
bx &
bx J
bx _
bx S
bx 8
bx >
bx I
bx O
bx 0
bx M
bx i
bx j
b1011 h
b110000 ,
b110000 Z
b110000 o
b110000 q
b101100 +
b101100 Y
b101100 [
b101100 l
1#
1;
#24
0#
0;
#25
b1100 h
b110100 ,
b110100 Z
b110100 o
b110100 q
b110000 +
b110000 Y
b110000 [
b110000 l
1#
1;
#26
0#
0;
#27
b1101 h
b111000 ,
b111000 Z
b111000 o
b111000 q
b110100 +
b110100 Y
b110100 [
b110100 l
1#
1;
#28
0#
0;
#29
b1110 h
b111100 ,
b111100 Z
b111100 o
b111100 q
b111000 +
b111000 Y
b111000 [
b111000 l
1#
1;
#30
0#
0;
#31
b1111 h
b1000000 ,
b1000000 Z
b1000000 o
b1000000 q
b111100 +
b111100 Y
b111100 [
b111100 l
1#
1;
#32
0#
0;
#33
b10000 h
b1000100 ,
b1000100 Z
b1000100 o
b1000100 q
b1000000 +
b1000000 Y
b1000000 [
b1000000 l
1#
1;
#34
0#
0;
#35
b10001 h
b1001000 ,
b1001000 Z
b1001000 o
b1001000 q
b1000100 +
b1000100 Y
b1000100 [
b1000100 l
1#
1;
#36
0#
0;
#37
b10010 h
b1001100 ,
b1001100 Z
b1001100 o
b1001100 q
b1001000 +
b1001000 Y
b1001000 [
b1001000 l
1#
1;
#38
0#
0;
#39
b10011 h
b1010000 ,
b1010000 Z
b1010000 o
b1010000 q
b1001100 +
b1001100 Y
b1001100 [
b1001100 l
1#
1;
#40
0#
0;
#41
b10100 h
b1010100 ,
b1010100 Z
b1010100 o
b1010100 q
b1010000 +
b1010000 Y
b1010000 [
b1010000 l
1#
1;
#42
0#
0;
#43
b10101 h
b1011000 ,
b1011000 Z
b1011000 o
b1011000 q
b1010100 +
b1010100 Y
b1010100 [
b1010100 l
1#
1;
#44
0#
0;
#45
b10110 h
b1011100 ,
b1011100 Z
b1011100 o
b1011100 q
b1011000 +
b1011000 Y
b1011000 [
b1011000 l
1#
1;
#46
0#
0;
#47
b10111 h
b1100000 ,
b1100000 Z
b1100000 o
b1100000 q
b1011100 +
b1011100 Y
b1011100 [
b1011100 l
1#
1;
#48
0#
0;
#49
b11000 h
b1100100 ,
b1100100 Z
b1100100 o
b1100100 q
b1100000 +
b1100000 Y
b1100000 [
b1100000 l
1#
1;
#50
0#
0;
#51
b11001 h
b1101000 ,
b1101000 Z
b1101000 o
b1101000 q
b1100100 +
b1100100 Y
b1100100 [
b1100100 l
1#
1;
#52
0#
0;
#53
b11010 h
b1101100 ,
b1101100 Z
b1101100 o
b1101100 q
b1101000 +
b1101000 Y
b1101000 [
b1101000 l
1#
1;
#54
0#
0;
#55
b11011 h
b1110000 ,
b1110000 Z
b1110000 o
b1110000 q
b1101100 +
b1101100 Y
b1101100 [
b1101100 l
1#
1;
#56
0#
0;
#57
b11100 h
b1110100 ,
b1110100 Z
b1110100 o
b1110100 q
b1110000 +
b1110000 Y
b1110000 [
b1110000 l
1#
1;
#58
0#
0;
#59
b11101 h
b1111000 ,
b1111000 Z
b1111000 o
b1111000 q
b1110100 +
b1110100 Y
b1110100 [
b1110100 l
1#
1;
#60
0#
0;
#61
b11110 h
b1111100 ,
b1111100 Z
b1111100 o
b1111100 q
b1111000 +
b1111000 Y
b1111000 [
b1111000 l
1#
1;
#62
0#
0;
#63
b11111 h
b10000000 ,
b10000000 Z
b10000000 o
b10000000 q
b1111100 +
b1111100 Y
b1111100 [
b1111100 l
1#
1;
#64
0#
0;
#65
b100000 h
b10000100 ,
b10000100 Z
b10000100 o
b10000100 q
b10000000 +
b10000000 Y
b10000000 [
b10000000 l
1#
1;
#66
0#
0;
#67
b100001 h
b10001000 ,
b10001000 Z
b10001000 o
b10001000 q
b10000100 +
b10000100 Y
b10000100 [
b10000100 l
1#
1;
#68
0#
0;
#69
b100010 h
b10001100 ,
b10001100 Z
b10001100 o
b10001100 q
b10001000 +
b10001000 Y
b10001000 [
b10001000 l
1#
1;
#70
0#
0;
#71
b100011 h
b10010000 ,
b10010000 Z
b10010000 o
b10010000 q
b10001100 +
b10001100 Y
b10001100 [
b10001100 l
1#
1;
#72
0#
0;
#73
b100100 h
b10010100 ,
b10010100 Z
b10010100 o
b10010100 q
b10010000 +
b10010000 Y
b10010000 [
b10010000 l
1#
1;
#74
0#
0;
#75
b100101 h
b10011000 ,
b10011000 Z
b10011000 o
b10011000 q
b10010100 +
b10010100 Y
b10010100 [
b10010100 l
1#
1;
#76
0#
0;
#77
b100110 h
b10011100 ,
b10011100 Z
b10011100 o
b10011100 q
b10011000 +
b10011000 Y
b10011000 [
b10011000 l
1#
1;
#78
0#
0;
#79
b100111 h
b10100000 ,
b10100000 Z
b10100000 o
b10100000 q
b10011100 +
b10011100 Y
b10011100 [
b10011100 l
1#
1;
#80
0#
0;
#81
b101000 h
b10100100 ,
b10100100 Z
b10100100 o
b10100100 q
b10100000 +
b10100000 Y
b10100000 [
b10100000 l
1#
1;
#82
0#
0;
#83
b101001 h
b10101000 ,
b10101000 Z
b10101000 o
b10101000 q
b10100100 +
b10100100 Y
b10100100 [
b10100100 l
1#
1;
#84
0#
0;
#85
b101010 h
b10101100 ,
b10101100 Z
b10101100 o
b10101100 q
b10101000 +
b10101000 Y
b10101000 [
b10101000 l
1#
1;
#86
0#
0;
#87
b101011 h
b10110000 ,
b10110000 Z
b10110000 o
b10110000 q
b10101100 +
b10101100 Y
b10101100 [
b10101100 l
1#
1;
#88
0#
0;
#89
b101100 h
b10110100 ,
b10110100 Z
b10110100 o
b10110100 q
b10110000 +
b10110000 Y
b10110000 [
b10110000 l
1#
1;
#90
0#
0;
#91
b101101 h
b10111000 ,
b10111000 Z
b10111000 o
b10111000 q
b10110100 +
b10110100 Y
b10110100 [
b10110100 l
1#
1;
#92
0#
0;
#93
b101110 h
b10111100 ,
b10111100 Z
b10111100 o
b10111100 q
b10111000 +
b10111000 Y
b10111000 [
b10111000 l
1#
1;
#94
0#
0;
#95
b101111 h
b11000000 ,
b11000000 Z
b11000000 o
b11000000 q
b10111100 +
b10111100 Y
b10111100 [
b10111100 l
1#
1;
#96
0#
0;
#97
b110000 h
b11000100 ,
b11000100 Z
b11000100 o
b11000100 q
b11000000 +
b11000000 Y
b11000000 [
b11000000 l
1#
1;
#98
0#
0;
#99
b110001 h
b11001000 ,
b11001000 Z
b11001000 o
b11001000 q
b11000100 +
b11000100 Y
b11000100 [
b11000100 l
1#
1;
#100
0#
0;
#101
b110010 h
b11001100 ,
b11001100 Z
b11001100 o
b11001100 q
b11001000 +
b11001000 Y
b11001000 [
b11001000 l
1#
1;
#102
0#
0;
