src/alu32.v
module alu32(
	input [31:0] A, B,		// Inputs
	input [1:0] Ctrl,			// For now only four operations supported
	output [31:0] Out,		// Operation result
	output zflg, ovflg, brwflg, negflg // Output characteristic flags
);

	reg [31:0] Out_;		// Operation result
	reg zflg_, ovflg_, brwflg_, negflg_; // Output characteristic flags

  initial begin
    zflg_ = 0;
    ovflg_ = 0;
    brwflg_ = 0;
    negflg_ = 0;
  end

	always @(*) begin
		case (Ctrl)
			// OR reg3, reg1, reg2 -> A = reg1, B = reg2
			4'b00: begin
				Out_ = A | B;
			end
			// SUBI reg4, reg5, 21 -> A = reg5, B = 21
			4'b01: begin
				Out_  = A - B;
			end
			// SW reg6, 5 (reg7) -> ???
			4'b10: begin
				Out_ = 0;	// Setting to 0 for now
			end
			// BEQ reg9, reg8, 7 -> ???
			4'b11:begin
				Out_ = 0; // Setting to 0 for now
			end
		endcase

		// Check for zero
		if (Out_ == 0) begin
			zflg_ = 1;
		end else begin zflg_ = 0; end
		// Check for negative result
		if (Out_[31] == 1) begin
			negflg_ = 1;
		end else begin negflg_ = 0; end
		// Check if borrow was required
		if (A < B) begin
			brwflg_ = 1;
		end
		// Check if overflow was there -> Not required right now
		ovflg_ = 0;
	end

	// Assign all reg's outputs
	assign Out = Out_;
	assign zflg = zflg_;
	assign ovflg = ovflg_;
	assign negflg = negflg_;
	assign brwflg = brwflg_;

endmodule

src/signextender16_32.v
module signextender16_32(
  input [15:0] inp,
  output [31:0] op
);

  reg [31:0] out_;

  initial begin
    out_ = 32'h00000000;
  end

  always @(*) begin
    out_ = {(inp[15] == 0) ? 16'h0000 : 16'hFFFF, inp};
  end

  assign op = out_;

endmodule

src/registerFile32x9.v
module registerFile32x9(
    input [3:0] readAddr1, readAddr2, writeAddr,
    input [31:0] writeData,
    input writeEnable, resetb, clk,
    output [31:0] readData1, readData2
);

    reg [31:0] registers [8:0];

    integer i;
    initial begin
        for(i = 0; i < 9; i = i + 1) begin
            registers[i] = 0;
        end
    end

    always @(posedge clk) begin
        if ((writeAddr < 9) && (writeEnable == 1)) begin
            registers[writeAddr] = writeData;
        end 
    end

    integer j;
    always @(negedge resetb) begin
        for (j = 0; j < 9; j = j + 1) begin
            registers[j] = 0;
        end
    end

    assign readData1 = (readAddr1 < 9) ? registers[readAddr1] : 32'hxxxxxxxx;
    assign readData2 = (readAddr2 < 9) ? registers[readAddr2] : 32'hxxxxxxxx;

endmodule

src/cu.v
module cu (
    input  [31:0] instr,
    output [1:0] aluCtrl,
    output [3:0] regFileReadAddr1, regFileReadAddr2, regFileWriteAddr,
    output aluSrc, regFileWriteEnable
);

  reg [1:0] aluCtrl_;
  reg regFileWriteEnable_;
  reg [3:0] regFileWriteAddr_;
  reg [3:0] regFileReadAddr1_, regFileReadAddr2_;
  reg aluSrc_;

  // OR outreg3, inreg1, inreg2 -> R-type
  // SUBI outreg4, inreg5, immval21 -> I-type
  // SW reg6, 5 (reg7) -> I-type (NOT IMPLEMENTED)
  // BEQ reg9, reg8, 7 -> J-type (NOT IMPLEMENTED)
  always @(*) begin
    casez (instr[31:26])
      // R-type (only OR)
      // 000000 5'b<Rd> 5'b<Rs> 5'b<Rt> 5'b<shamt> 6'b<funct>
      6'b000000: begin
        // Only OR as R-type supported as of now hence we set undef
        aluCtrl_ = 2'b00;
        regFileWriteAddr_ = instr[25:21];
        regFileWriteEnable_ = 1;
        regFileReadAddr1_ = instr[20:16];
        regFileReadAddr2_ = instr[15:11];
        aluSrc_ = 0;
      end
      // I-type (SUBI only for now)
      // 000001 5'b<Rd> 5'b<rS> 16'b<ImmVal>
      6'b000001: begin
        aluCtrl_ = 2'b01;
        regFileWriteAddr_ = instr[25:21];
        regFileWriteEnable_ = 1;
        regFileReadAddr1_ = instr[20:16];
        regFileReadAddr2_ = 5'bzzzzz;
        aluSrc_ = 1;
      end
      default: begin
        aluCtrl_ = 2'bxx;
        regFileWriteAddr_ = 5'bxxxxx;
        regFileWriteEnable_ = 1'bx;
        regFileReadAddr1_ = 5'bxxxxx;
        regFileReadAddr2_ = 5'bxxxxx;
        aluSrc_ = 1'bx;
      end
    endcase
  end

  assign aluCtrl = aluCtrl_;
  assign regFileWriteAddr = regFileWriteAddr_;
  assign regFileWriteEnable = regFileWriteEnable_;
  assign regFileReadAddr1 = regFileReadAddr1_;
  assign regFileReadAddr2 = regFileReadAddr2_;
  assign aluSrc = aluSrc_;

endmodule

src/ROM32.v
module ROM32(
    input [31:0] addr,
    input ce, 
    output [31:0] out
);

    reg [31:0] ROM_ [0:31];

    integer i;

    // Program 
    initial begin

        for (i = 0; i < 32; i = i + 1) begin
          ROM_[i]  = 32'h00000000;
        end

        // OR $1, $2, $3 => $1 = $2 | $3;
        ROM_[0] = 32'b00000000001000100001100000000000;
        // SUBI $1, $2, 21 => $1 = $2 - 21;
        ROM_[1] = 32'h04220015;
        // SUBI $2, $1, 0xFFFFFFEA => $1 = $2 - 0xFFFFFFEA; -> Answer will be 1
        ROM_[2] = 32'b00000100010000101111111111101010;
        // OR $3, $1, $2 => $4 = $1 | $7
        ROM_[3] = 32'b00000000011000010001000000000000;
    end

    reg [31:0] out_;

    always @(*) begin
      if (ce == 1) begin
        out_ = (addr < 11) ? ROM_[addr] : 32'hx;
      end
    end

    assign out = out_;

endmodule

register32.v
module register32(
    input [31:0] ip, 
    input wen, resb,
    output [31:0] op
);

    reg [31:0] register;

    always @(posedge wen or negedge resb) begin
        if (wen == 1) begin
            register = ip;
        end 
        
        if (resb == 0) begin
            register = 0;
        end 

        if (wen == 1 && resb == 0) begin
            register = 32'bz;
        end
    end

    assign op = register;
endmodule

src/add32.v
module add32(
    input [31:0] A, B,
    input Cin,
    output [31:0] Sum,
    output Cout
); 

    reg [31:0] _Sum_;
    reg _Cout_;

    always @(*) begin
        {_Cout_, _Sum_} = A + B + Cin;
    end

    assign Sum = _Sum_;
    assign Cout = _Cout_;

endmodule

src/Proc.v
module Proc (
    input reset
);

    reg clk;

    initial clk = 0;

    always begin
        #1;
        clk = ~clk;
    end

    wire [31:0] pcIp;
    wire pcWen, pcResb;
    assign pcResb = reset;
    assign pcWen = clk;

    wire [31:0] pcOp;

    wire pcCout;
    add32 pcAdder(
        .A(pcOp), .B(32'h00000004), .Cin(1'b0),
        .Sum(pcIp), .Cout(pcCout)
    );

    register32 PC(
        .ip(pcIp), .wen(pcWen), .resb(pcResb),
        .op(pcOp)
    );

    wire [31:0] instr_;
    ROM32 instrMem(
        .addr(pcOp >> 2), .ce(clk), .out(instr_)
    );

    wire [1:0] aluCtrl_;
    wire [3:0] regFileReadAddr1_, regFileReadAddr2_, regFileWriteAddr_;
    wire aluSrc_, regFileWriteEnable_;
    cu CU(
      .instr(instr_),
      .aluCtrl(aluCtrl_),
      .regFileWriteAddr(regFileWriteAddr_),
      .regFileWriteEnable(regFileWriteEnable_),
      .regFileReadAddr1(regFileReadAddr1_), .regFileReadAddr2(regFileReadAddr2_),
      .aluSrc(aluSrc_)
    );

	  wire [31:0] aluOut_;		// Operation result

    wire [31:0] regFileReadData1_, regFileReadData2_;
    registerFile32x9 REGISTERFILE(
      .readAddr1(regFileReadAddr1_), 
      .readAddr2(regFileReadAddr2_),
      .writeAddr(regFileWriteAddr_),
      .writeData(aluOut_),
      .writeEnable(regFileWriteEnable_),
      .resetb(1'b1),
      .readData1(regFileReadData1_),
      .readData2(regFileReadData2_),
      .clk(clk)
    );


    wire [31:0] aluImmVal;
    signextender16_32 SIGNEXTEND16_32(
      .inp(instr_[15:0]), .op(aluImmVal)
    );

	  wire zflg, ovflg, brwflg, negflg; // Output characteristic flags
    alu32 ALU(
      .A(regFileReadData1_), 
      .B((aluSrc_ == 1) ? aluImmVal : regFileReadData2_), 
      .Ctrl(aluCtrl_),
      .Out(aluOut_), 
      .zflg(zflg), 
      .ovflg(ovflg), 
      .brwflg(brwflg), 
      .negflg(negflg)
    );

endmodule

tb/Proctb.v
module Proctb();

    reg reset;

    Proc uut(
        .reset(reset)
    );

    initial begin
        $dumpfile("build/Proctb.vcd");
        $dumpvars(0, Proctb);
        reset = 0;   // reset active
        #2; reset = 1; // release reset
        #100;
        $finish;
    end

endmodule

build/Proctb.vcd
$date
	Wed Mar  4 16:45:06 2026
$end
$version
	Icarus Verilog
$end
$timescale
	1s
$end
$scope module Proctb $end
$var reg 1 ! reset $end
$scope module uut $end
$var wire 1 " pcResb $end
$var wire 1 # pcWen $end
$var wire 1 ! reset $end
$var wire 1 $ zflg $end
$var wire 1 % regFileWriteEnable_ $end
$var wire 4 & regFileWriteAddr_ [3:0] $end
$var wire 32 ' regFileReadData2_ [31:0] $end
$var wire 32 ( regFileReadData1_ [31:0] $end
$var wire 4 ) regFileReadAddr2_ [3:0] $end
$var wire 4 * regFileReadAddr1_ [3:0] $end
$var wire 32 + pcOp [31:0] $end
$var wire 32 , pcIp [31:0] $end
$var wire 1 - pcCout $end
$var wire 1 . ovflg $end
$var wire 1 / negflg $end
$var wire 32 0 instr_ [31:0] $end
$var wire 1 1 brwflg $end
$var wire 1 2 aluSrc_ $end
$var wire 32 3 aluOut_ [31:0] $end
$var wire 32 4 aluImmVal [31:0] $end
$var wire 2 5 aluCtrl_ [1:0] $end
$var reg 1 6 clk $end
$scope module ALU $end
$var wire 32 7 B [31:0] $end
$var wire 32 8 Out [31:0] $end
$var wire 1 1 brwflg $end
$var wire 1 / negflg $end
$var wire 1 . ovflg $end
$var wire 1 $ zflg $end
$var wire 2 9 Ctrl [1:0] $end
$var wire 32 : A [31:0] $end
$var reg 32 ; Out_ [31:0] $end
$var reg 1 < brwflg_ $end
$var reg 1 = negflg_ $end
$var reg 1 > ovflg_ $end
$var reg 1 ? zflg_ $end
$upscope $end
$scope module CU $end
$var wire 2 @ aluCtrl [1:0] $end
$var wire 4 A regFileWriteAddr [3:0] $end
$var wire 1 % regFileWriteEnable $end
$var wire 4 B regFileReadAddr2 [3:0] $end
$var wire 4 C regFileReadAddr1 [3:0] $end
$var wire 32 D instr [31:0] $end
$var wire 1 2 aluSrc $end
$var reg 2 E aluCtrl_ [1:0] $end
$var reg 1 2 aluSrc_ $end
$var reg 4 F regFileReadAddr1_ [3:0] $end
$var reg 4 G regFileReadAddr2_ [3:0] $end
$var reg 4 H regFileWriteAddr_ [3:0] $end
$var reg 1 I regFileWriteEnable_ $end
$upscope $end
$scope module PC $end
$var wire 1 " resb $end
$var wire 1 # wen $end
$var wire 32 J op [31:0] $end
$var wire 32 K ip [31:0] $end
$var reg 32 L register [31:0] $end
$upscope $end
$scope module REGISTERFILE $end
$var wire 1 6 clk $end
$var wire 4 M readAddr1 [3:0] $end
$var wire 4 N readAddr2 [3:0] $end
$var wire 1 O resetb $end
$var wire 4 P writeAddr [3:0] $end
$var wire 32 Q writeData [31:0] $end
$var wire 1 % writeEnable $end
$var wire 32 R readData2 [31:0] $end
$var wire 32 S readData1 [31:0] $end
$var integer 32 T i [31:0] $end
$var integer 32 U j [31:0] $end
$upscope $end
$scope module SIGNEXTEND16_32 $end
$var wire 16 V inp [15:0] $end
$var wire 32 W op [31:0] $end
$var reg 32 X out_ [31:0] $end
$upscope $end
$scope module instrMem $end
$var wire 32 Y addr [31:0] $end
$var wire 1 6 ce $end
$var wire 32 Z out [31:0] $end
$var reg 32 [ out_ [31:0] $end
$var integer 32 \ i [31:0] $end
$upscope $end
$scope module pcAdder $end
$var wire 32 ] A [31:0] $end
$var wire 32 ^ B [31:0] $end
$var wire 1 _ Cin $end
$var wire 1 - Cout $end
$var wire 32 ` Sum [31:0] $end
$var reg 1 a _Cout_ $end
$var reg 32 b _Sum_ [31:0] $end
$upscope $end
$upscope $end
$upscope $end
$enddefinitions $end
$comment Show the parameter values. $end
$dumpall
$end
#0
$dumpvars
b100 b
0a
b100 `
0_
b100 ^
b0 ]
b100000 \
bx [
bx Z
b0 Y
b0 X
b0 W
bx V
bx U
b1001 T
bx S
bx R
bx Q
bx P
1O
bx N
bx M
b0 L
b100 K
b0 J
xI
bx H
bx G
bx F
bx E
bx D
bx C
bx B
bx A
bx @
0?
0>
0=
0<
bx ;
bx :
bx 9
bx 8
bx 7
06
bx 5
b0 4
bx 3
x2
01
bx 0
0/
0.
0-
b100 ,
b0 +
bx *
bx )
bx (
bx '
bx &
x%
0$
0#
0"
0!
$end
#1
1$
1?
b0 3
b0 8
b0 Q
b0 ;
b1100000000000 4
b1100000000000 W
b1100000000000 X
b0 7
b0 '
b0 R
b0 (
b0 :
b0 S
b1100000000000 V
02
b11 )
b11 B
b11 G
b11 N
b10 *
b10 C
b10 F
b10 M
1%
1I
b1 &
b1 A
b1 P
b1 H
b0 5
b0 9
b0 @
b0 E
b1000100001100000000000 0
b1000100001100000000000 D
b1000100001100000000000 Z
b1000100001100000000000 [
1#
16
#2
0#
06
1"
1!
#3
11
1<
1/
1=
0$
0?
b11111111111111111111111111101011 3
b11111111111111111111111111101011 8
b11111111111111111111111111101011 Q
b11111111111111111111111111101011 ;
b10101 4
b10101 W
b10101 X
b10101 7
bx '
bx R
b10101 V
12
bz )
bz B
bz G
bz N
b1 5
b1 9
b1 @
b1 E
b100001000100000000000010101 0
b100001000100000000000010101 D
b100001000100000000000010101 Z
b100001000100000000000010101 [
b1 Y
b1000 ,
b1000 K
b1000 `
b1000 b
b100 +
b100 J
b100 L
b100 ]
1#
16
#4
0#
06
#5
0/
0=
b10110 3
b10110 8
b10110 Q
b10110 ;
b11111111111111111111111111101010 7
b11111111111111111111111111101010 4
b11111111111111111111111111101010 W
b11111111111111111111111111101010 X
b1111111111101010 V
b10 &
b10 A
b10 P
b10 H
b100010000101111111111101010 0
b100010000101111111111101010 D
b100010000101111111111101010 Z
b100010000101111111111101010 [
b10 Y
b1100 ,
b1100 K
b1100 `
b1100 b
b1000 +
b1000 J
b1000 L
b1000 ]
1#
16
#6
0#
06
#7
b1000000000000 4
b1000000000000 W
b1000000000000 X
b10110 7
b10110 '
b10110 R
1/
1=
b1000000000000 V
02
b10 )
b10 B
b10 G
b10 N
b1 *
b1 C
b1 F
b1 M
b11 &
b11 A
b11 P
b11 H
b0 5
b0 9
b0 @
b0 E
b11000010001000000000000 0
b11000010001000000000000 D
b11000010001000000000000 Z
b11000010001000000000000 [
b11 Y
b10000 ,
b10000 K
b10000 `
b10000 b
b1100 +
b1100 J
b1100 L
b1100 ]
b11111111111111111111111111111111 3
b11111111111111111111111111111111 8
b11111111111111111111111111111111 Q
b11111111111111111111111111111111 ;
b11111111111111111111111111101011 (
b11111111111111111111111111101011 :
b11111111111111111111111111101011 S
1#
16
#8
0#
06
#9
1$
1?
b0 7
0/
0=
b0 3
b0 8
b0 Q
b0 ;
b0 4
b0 W
b0 X
b0 '
b0 R
b0 (
b0 :
b0 S
b0 V
b0 )
b0 B
b0 G
b0 N
b0 *
b0 C
b0 F
b0 M
b0 &
b0 A
b0 P
b0 H
b0 0
b0 D
b0 Z
b0 [
b100 Y
b10100 ,
b10100 K
b10100 `
b10100 b
b10000 +
b10000 J
b10000 L
b10000 ]
1#
16
#10
0#
06
#11
b101 Y
b11000 ,
b11000 K
b11000 `
b11000 b
b10100 +
b10100 J
b10100 L
b10100 ]
1#
16
#12
0#
06
#13
b110 Y
b11100 ,
b11100 K
b11100 `
b11100 b
b11000 +
b11000 J
b11000 L
b11000 ]
1#
16
#14
0#
06
#15
b111 Y
b100000 ,
b100000 K
b100000 `
b100000 b
b11100 +
b11100 J
b11100 L
b11100 ]
1#
16
#16
0#
06
#17
b1000 Y
b100100 ,
b100100 K
b100100 `
b100100 b
b100000 +
b100000 J
b100000 L
b100000 ]
1#
16
#18
0#
06
#19
b1001 Y
b101000 ,
b101000 K
b101000 `
b101000 b
b100100 +
b100100 J
b100100 L
b100100 ]
1#
16
#20
0#
06
#21
b1010 Y
b101100 ,
b101100 K
b101100 `
b101100 b
b101000 +
b101000 J
b101000 L
b101000 ]
1#
16
#22
0#
06
#23
bx 4
bx W
bx X
bx 7
bx '
bx R
bx (
bx :
bx S
bx V
x2
bx )
bx B
bx G
bx N
bx *
bx C
bx F
bx M
x%
xI
bx &
bx A
bx P
bx H
bx 5
bx 9
bx @
bx E
bx 0
bx D
bx Z
bx [
b1011 Y
b110000 ,
b110000 K
b110000 `
b110000 b
b101100 +
b101100 J
b101100 L
b101100 ]
1#
16
#24
0#
06
#25
b1100 Y
b110100 ,
b110100 K
b110100 `
b110100 b
b110000 +
b110000 J
b110000 L
b110000 ]
1#
16
#26
0#
06
#27
b1101 Y
b111000 ,
b111000 K
b111000 `
b111000 b
b110100 +
b110100 J
b110100 L
b110100 ]
1#
16
#28
0#
06
#29
b1110 Y
b111100 ,
b111100 K
b111100 `
b111100 b
b111000 +
b111000 J
b111000 L
b111000 ]
1#
16
#30
0#
06
#31
b1111 Y
b1000000 ,
b1000000 K
b1000000 `
b1000000 b
b111100 +
b111100 J
b111100 L
b111100 ]
1#
16
#32
0#
06
#33
b10000 Y
b1000100 ,
b1000100 K
b1000100 `
b1000100 b
b1000000 +
b1000000 J
b1000000 L
b1000000 ]
1#
16
#34
0#
06
#35
b10001 Y
b1001000 ,
b1001000 K
b1001000 `
b1001000 b
b1000100 +
b1000100 J
b1000100 L
b1000100 ]
1#
16
#36
0#
06
#37
b10010 Y
b1001100 ,
b1001100 K
b1001100 `
b1001100 b
b1001000 +
b1001000 J
b1001000 L
b1001000 ]
1#
16
#38
0#
06
#39
b10011 Y
b1010000 ,
b1010000 K
b1010000 `
b1010000 b
b1001100 +
b1001100 J
b1001100 L
b1001100 ]
1#
16
#40
0#
06
#41
b10100 Y
b1010100 ,
b1010100 K
b1010100 `
b1010100 b
b1010000 +
b1010000 J
b1010000 L
b1010000 ]
1#
16
#42
0#
06
#43
b10101 Y
b1011000 ,
b1011000 K
b1011000 `
b1011000 b
b1010100 +
b1010100 J
b1010100 L
b1010100 ]
1#
16
#44
0#
06
#45
b10110 Y
b1011100 ,
b1011100 K
b1011100 `
b1011100 b
b1011000 +
b1011000 J
b1011000 L
b1011000 ]
1#
16
#46
0#
06
#47
b10111 Y
b1100000 ,
b1100000 K
b1100000 `
b1100000 b
b1011100 +
b1011100 J
b1011100 L
b1011100 ]
1#
16
#48
0#
06
#49
b11000 Y
b1100100 ,
b1100100 K
b1100100 `
b1100100 b
b1100000 +
b1100000 J
b1100000 L
b1100000 ]
1#
16
#50
0#
06
#51
b11001 Y
b1101000 ,
b1101000 K
b1101000 `
b1101000 b
b1100100 +
b1100100 J
b1100100 L
b1100100 ]
1#
16
#52
0#
06
#53
b11010 Y
b1101100 ,
b1101100 K
b1101100 `
b1101100 b
b1101000 +
b1101000 J
b1101000 L
b1101000 ]
1#
16
#54
0#
06
#55
b11011 Y
b1110000 ,
b1110000 K
b1110000 `
b1110000 b
b1101100 +
b1101100 J
b1101100 L
b1101100 ]
1#
16
#56
0#
06
#57
b11100 Y
b1110100 ,
b1110100 K
b1110100 `
b1110100 b
b1110000 +
b1110000 J
b1110000 L
b1110000 ]
1#
16
#58
0#
06
#59
b11101 Y
b1111000 ,
b1111000 K
b1111000 `
b1111000 b
b1110100 +
b1110100 J
b1110100 L
b1110100 ]
1#
16
#60
0#
06
#61
b11110 Y
b1111100 ,
b1111100 K
b1111100 `
b1111100 b
b1111000 +
b1111000 J
b1111000 L
b1111000 ]
1#
16
#62
0#
06
#63
b11111 Y
b10000000 ,
b10000000 K
b10000000 `
b10000000 b
b1111100 +
b1111100 J
b1111100 L
b1111100 ]
1#
16
#64
0#
06
#65
b100000 Y
b10000100 ,
b10000100 K
b10000100 `
b10000100 b
b10000000 +
b10000000 J
b10000000 L
b10000000 ]
1#
16
#66
0#
06
#67
b100001 Y
b10001000 ,
b10001000 K
b10001000 `
b10001000 b
b10000100 +
b10000100 J
b10000100 L
b10000100 ]
1#
16
#68
0#
06
#69
b100010 Y
b10001100 ,
b10001100 K
b10001100 `
b10001100 b
b10001000 +
b10001000 J
b10001000 L
b10001000 ]
1#
16
#70
0#
06
#71
b100011 Y
b10010000 ,
b10010000 K
b10010000 `
b10010000 b
b10001100 +
b10001100 J
b10001100 L
b10001100 ]
1#
16
#72
0#
06
#73
b100100 Y
b10010100 ,
b10010100 K
b10010100 `
b10010100 b
b10010000 +
b10010000 J
b10010000 L
b10010000 ]
1#
16
#74
0#
06
#75
b100101 Y
b10011000 ,
b10011000 K
b10011000 `
b10011000 b
b10010100 +
b10010100 J
b10010100 L
b10010100 ]
1#
16
#76
0#
06
#77
b100110 Y
b10011100 ,
b10011100 K
b10011100 `
b10011100 b
b10011000 +
b10011000 J
b10011000 L
b10011000 ]
1#
16
#78
0#
06
#79
b100111 Y
b10100000 ,
b10100000 K
b10100000 `
b10100000 b
b10011100 +
b10011100 J
b10011100 L
b10011100 ]
1#
16
#80
0#
06
#81
b101000 Y
b10100100 ,
b10100100 K
b10100100 `
b10100100 b
b10100000 +
b10100000 J
b10100000 L
b10100000 ]
1#
16
#82
0#
06
#83
b101001 Y
b10101000 ,
b10101000 K
b10101000 `
b10101000 b
b10100100 +
b10100100 J
b10100100 L
b10100100 ]
1#
16
#84
0#
06
#85
b101010 Y
b10101100 ,
b10101100 K
b10101100 `
b10101100 b
b10101000 +
b10101000 J
b10101000 L
b10101000 ]
1#
16
#86
0#
06
#87
b101011 Y
b10110000 ,
b10110000 K
b10110000 `
b10110000 b
b10101100 +
b10101100 J
b10101100 L
b10101100 ]
1#
16
#88
0#
06
#89
b101100 Y
b10110100 ,
b10110100 K
b10110100 `
b10110100 b
b10110000 +
b10110000 J
b10110000 L
b10110000 ]
1#
16
#90
0#
06
#91
b101101 Y
b10111000 ,
b10111000 K
b10111000 `
b10111000 b
b10110100 +
b10110100 J
b10110100 L
b10110100 ]
1#
16
#92
0#
06
#93
b101110 Y
b10111100 ,
b10111100 K
b10111100 `
b10111100 b
b10111000 +
b10111000 J
b10111000 L
b10111000 ]
1#
16
#94
0#
06
#95
b101111 Y
b11000000 ,
b11000000 K
b11000000 `
b11000000 b
b10111100 +
b10111100 J
b10111100 L
b10111100 ]
1#
16
#96
0#
06
#97
b110000 Y
b11000100 ,
b11000100 K
b11000100 `
b11000100 b
b11000000 +
b11000000 J
b11000000 L
b11000000 ]
1#
16
#98
0#
06
#99
b110001 Y
b11001000 ,
b11001000 K
b11001000 `
b11001000 b
b11000100 +
b11000100 J
b11000100 L
b11000100 ]
1#
16
#100
0#
06
#101
b110010 Y
b11001100 ,
b11001100 K
b11001100 `
b11001100 b
b11001000 +
b11001000 J
b11001000 L
b11001000 ]
1#
16
#102
0#
06
