ROM32.v
module ROM32(
    input [31:0] addr,
    input ce, 
    output [31:0] out
);

    reg [31:0] ROM_ [0:31];

    // Program 
    initial begin
        ROM_[0] = 32'hFEEDBEEF;
        ROM_[1] = 32'hDEEFFFEB;
        ROM_[2] = 32'hABACADAB;
        ROM_[3] = 32'hFEEDBEEF;
        ROM_[4] = 32'hDEEFFFEB;
        ROM_[5] = 32'hABACADAB;
        ROM_[6] = 32'hFEEDBEEF;
        ROM_[7] = 32'hDEEFFFEB;
        ROM_[8] = 32'hABACADAB;
        ROM_[9] = 32'hDEEFFFEB;
        ROM_[10] = 32'hABACADAB;
    end

    reg [31:0] out_;

    always @(addr) begin
        if (ce == 1) begin
            out_ = ROM_[addr];
        end else begin out_ = 32'hzzzzzzzz; end
    end

    assign out = out_;

endmodule

register32.v
module register32(
    input [31:0] ip, 
    input wen, resb,
    output [31:0] op
);

    reg [31:0] register;

    always @(posedge wen or negedge resb) begin
        if (wen == 1) begin
            register = ip;
        end 
        
        if (resb == 0) begin
            register = 0;
        end 

        if (wen == 1 && resb == 0) begin
            register = 32'bz;
        end
    end

    assign op = register;
endmodule

src/add32.v
module add32(
    input [31:0] A, B,
    input Cin,
    output [31:0] Sum,
    output Cout
); 

    reg [31:0] _Sum_;
    reg _Cout_;

    always @(*) begin
        {_Cout_, _Sum_} = A + B + Cin;
    end

    assign Sum = _Sum_;
    assign Cout = _Cout_;

endmodule

src/Proc.v
module Proc (
    input reset, 
    output [31:0] instr
);

    reg clk;

    initial clk = 0;

    always begin
        #1;
        clk = ~clk;
    end

    wire [31:0] pcIp;
    wire pcWen, pcResb;
    assign pcResb = reset;
    assign pcWen = clk;

    wire [31:0] pcOp;

    wire pcCout;
    add32 pcAdder(
        .A(pcOp), .B(32'h00000004), .Cin(1'b0),
        .Sum(pcIp), .Cout(pcCout)
    );

    register32 PC(
        .ip(pcIp), .wen(pcWen), .resb(pcResb),
        .op(pcOp)
    );

    wire [31:0] instr_;
    ROM32 instrMem(
        .addr(pcOp), .ce(clk), .out(instr_)
    );

    assign instr = instr_;

endmodule

tb/Proctb.v
module Proctb();

    reg reset;
    wire [31:0] instr;

    Proc uut(
        .reset(reset),
        .instr(instr)
    );

    initial begin
        $dumpfile("build/Proctb.vcd");
        $dumpvars(0, Proctb);
        reset = 0;   // reset active
        #2; reset = 1; // release reset
        #100;
        $finish;
    end

endmodule

build/Proctb.vcd
$date
	Sun Feb 22 20:35:28 2026
$end
$version
	Icarus Verilog
$end
$timescale
	1s
$end
$scope module Proctb $end
$var wire 32 ! instr [31:0] $end
$var reg 1 " reset $end
$scope module uut $end
$var wire 32 # instr [31:0] $end
$var wire 1 $ pcResb $end
$var wire 1 % pcWen $end
$var wire 1 " reset $end
$var wire 32 & pcOp [31:0] $end
$var wire 32 ' pcIp [31:0] $end
$var wire 1 ( pcCout $end
$var wire 32 ) instr_ [31:0] $end
$var reg 1 * clk $end
$scope module PC $end
$var wire 32 + op [31:0] $end
$var wire 1 $ resb $end
$var wire 1 % wen $end
$var wire 32 , ip [31:0] $end
$var reg 32 - register [31:0] $end
$upscope $end
$scope module instrMem $end
$var wire 32 . addr [31:0] $end
$var wire 1 * ce $end
$var wire 32 / out [31:0] $end
$var reg 32 0 out_ [31:0] $end
$upscope $end
$scope module pcAdder $end
$var wire 32 1 A [31:0] $end
$var wire 32 2 B [31:0] $end
$var wire 1 3 Cin $end
$var wire 1 ( Cout $end
$var wire 32 4 Sum [31:0] $end
$var reg 1 5 _Cout_ $end
$var reg 32 6 _Sum_ [31:0] $end
$upscope $end
$upscope $end
$upscope $end
$enddefinitions $end
$comment Show the parameter values. $end
$dumpall
$end
#0
$dumpvars
b100 6
05
b100 4
03
b100 2
b0 1
bz 0
bz /
b0 .
b0 -
b100 ,
b0 +
0*
bz )
0(
b100 '
b0 &
0%
0$
bz #
0"
bz !
$end
#1
1%
1*
#2
0%
0*
1$
1"
#3
b11011110111011111111111111101011 !
b11011110111011111111111111101011 #
b11011110111011111111111111101011 )
b11011110111011111111111111101011 /
b11011110111011111111111111101011 0
b1000 '
b1000 ,
b1000 4
b1000 6
b100 &
b100 +
b100 .
b100 1
b100 -
1%
1*
#4
0%
0*
#5
b10101011101011001010110110101011 !
b10101011101011001010110110101011 #
b10101011101011001010110110101011 )
b10101011101011001010110110101011 /
b10101011101011001010110110101011 0
b1100 '
b1100 ,
b1100 4
b1100 6
b1000 &
b1000 +
b1000 .
b1000 1
b1000 -
1%
1*
#6
0%
0*
#7
b11111110111011011011111011101111 !
b11111110111011011011111011101111 #
b11111110111011011011111011101111 )
b11111110111011011011111011101111 /
b11111110111011011011111011101111 0
b10000 '
b10000 ,
b10000 4
b10000 6
b1100 &
b1100 +
b1100 .
b1100 1
b1100 -
1%
1*
#8
0%
0*
#9
b11011110111011111111111111101011 !
b11011110111011111111111111101011 #
b11011110111011111111111111101011 )
b11011110111011111111111111101011 /
b11011110111011111111111111101011 0
b10100 '
b10100 ,
b10100 4
b10100 6
b10000 &
b10000 +
b10000 .
b10000 1
b10000 -
1%
1*
#10
0%
0*
#11
b10101011101011001010110110101011 !
b10101011101011001010110110101011 #
b10101011101011001010110110101011 )
b10101011101011001010110110101011 /
b10101011101011001010110110101011 0
b11000 '
b11000 ,
b11000 4
b11000 6
b10100 &
b10100 +
b10100 .
b10100 1
b10100 -
1%
1*
#12
0%
0*
#13
b11111110111011011011111011101111 !
b11111110111011011011111011101111 #
b11111110111011011011111011101111 )
b11111110111011011011111011101111 /
b11111110111011011011111011101111 0
b11100 '
b11100 ,
b11100 4
b11100 6
b11000 &
b11000 +
b11000 .
b11000 1
b11000 -
1%
1*
#14
0%
0*
#15
b11011110111011111111111111101011 !
b11011110111011111111111111101011 #
b11011110111011111111111111101011 )
b11011110111011111111111111101011 /
b11011110111011111111111111101011 0
b100000 '
b100000 ,
b100000 4
b100000 6
b11100 &
b11100 +
b11100 .
b11100 1
b11100 -
1%
1*
#16
0%
0*
#17
b10101011101011001010110110101011 !
b10101011101011001010110110101011 #
b10101011101011001010110110101011 )
b10101011101011001010110110101011 /
b10101011101011001010110110101011 0
b100100 '
b100100 ,
b100100 4
b100100 6
b100000 &
b100000 +
b100000 .
b100000 1
b100000 -
1%
1*
#18
0%
0*
#19
b11011110111011111111111111101011 !
b11011110111011111111111111101011 #
b11011110111011111111111111101011 )
b11011110111011111111111111101011 /
b11011110111011111111111111101011 0
b101000 '
b101000 ,
b101000 4
b101000 6
b100100 &
b100100 +
b100100 .
b100100 1
b100100 -
1%
1*
#20
0%
0*
#21
b10101011101011001010110110101011 !
b10101011101011001010110110101011 #
b10101011101011001010110110101011 )
b10101011101011001010110110101011 /
b10101011101011001010110110101011 0
b101100 '
b101100 ,
b101100 4
b101100 6
b101000 &
b101000 +
b101000 .
b101000 1
b101000 -
1%
1*
#22
0%
0*
#23
bx !
bx #
bx )
bx /
bx 0
b110000 '
b110000 ,
b110000 4
b110000 6
b101100 &
b101100 +
b101100 .
b101100 1
b101100 -
1%
1*
#24
0%
0*
#25
b110100 '
b110100 ,
b110100 4
b110100 6
b110000 &
b110000 +
b110000 .
b110000 1
b110000 -
1%
1*
#26
0%
0*
#27
b111000 '
b111000 ,
b111000 4
b111000 6
b110100 &
b110100 +
b110100 .
b110100 1
b110100 -
1%
1*
#28
0%
0*
#29
b111100 '
b111100 ,
b111100 4
b111100 6
b111000 &
b111000 +
b111000 .
b111000 1
b111000 -
1%
1*
#30
0%
0*
#31
b1000000 '
b1000000 ,
b1000000 4
b1000000 6
b111100 &
b111100 +
b111100 .
b111100 1
b111100 -
1%
1*
#32
0%
0*
#33
b1000100 '
b1000100 ,
b1000100 4
b1000100 6
b1000000 &
b1000000 +
b1000000 .
b1000000 1
b1000000 -
1%
1*
#34
0%
0*
#35
b1001000 '
b1001000 ,
b1001000 4
b1001000 6
b1000100 &
b1000100 +
b1000100 .
b1000100 1
b1000100 -
1%
1*
#36
0%
0*
#37
b1001100 '
b1001100 ,
b1001100 4
b1001100 6
b1001000 &
b1001000 +
b1001000 .
b1001000 1
b1001000 -
1%
1*
#38
0%
0*
#39
b1010000 '
b1010000 ,
b1010000 4
b1010000 6
b1001100 &
b1001100 +
b1001100 .
b1001100 1
b1001100 -
1%
1*
#40
0%
0*
#41
b1010100 '
b1010100 ,
b1010100 4
b1010100 6
b1010000 &
b1010000 +
b1010000 .
b1010000 1
b1010000 -
1%
1*
#42
0%
0*
#43
b1011000 '
b1011000 ,
b1011000 4
b1011000 6
b1010100 &
b1010100 +
b1010100 .
b1010100 1
b1010100 -
1%
1*
#44
0%
0*
#45
b1011100 '
b1011100 ,
b1011100 4
b1011100 6
b1011000 &
b1011000 +
b1011000 .
b1011000 1
b1011000 -
1%
1*
#46
0%
0*
#47
b1100000 '
b1100000 ,
b1100000 4
b1100000 6
b1011100 &
b1011100 +
b1011100 .
b1011100 1
b1011100 -
1%
1*
#48
0%
0*
#49
b1100100 '
b1100100 ,
b1100100 4
b1100100 6
b1100000 &
b1100000 +
b1100000 .
b1100000 1
b1100000 -
1%
1*
#50
0%
0*
#51
b1101000 '
b1101000 ,
b1101000 4
b1101000 6
b1100100 &
b1100100 +
b1100100 .
b1100100 1
b1100100 -
1%
1*
#52
0%
0*
#53
b1101100 '
b1101100 ,
b1101100 4
b1101100 6
b1101000 &
b1101000 +
b1101000 .
b1101000 1
b1101000 -
1%
1*
#54
0%
0*
#55
b1110000 '
b1110000 ,
b1110000 4
b1110000 6
b1101100 &
b1101100 +
b1101100 .
b1101100 1
b1101100 -
1%
1*
#56
0%
0*
#57
b1110100 '
b1110100 ,
b1110100 4
b1110100 6
b1110000 &
b1110000 +
b1110000 .
b1110000 1
b1110000 -
1%
1*
#58
0%
0*
#59
b1111000 '
b1111000 ,
b1111000 4
b1111000 6
b1110100 &
b1110100 +
b1110100 .
b1110100 1
b1110100 -
1%
1*
#60
0%
0*
#61
b1111100 '
b1111100 ,
b1111100 4
b1111100 6
b1111000 &
b1111000 +
b1111000 .
b1111000 1
b1111000 -
1%
1*
#62
0%
0*
#63
b10000000 '
b10000000 ,
b10000000 4
b10000000 6
b1111100 &
b1111100 +
b1111100 .
b1111100 1
b1111100 -
1%
1*
#64
0%
0*
#65
b10000100 '
b10000100 ,
b10000100 4
b10000100 6
b10000000 &
b10000000 +
b10000000 .
b10000000 1
b10000000 -
1%
1*
#66
0%
0*
#67
b10001000 '
b10001000 ,
b10001000 4
b10001000 6
b10000100 &
b10000100 +
b10000100 .
b10000100 1
b10000100 -
1%
1*
#68
0%
0*
#69
b10001100 '
b10001100 ,
b10001100 4
b10001100 6
b10001000 &
b10001000 +
b10001000 .
b10001000 1
b10001000 -
1%
1*
#70
0%
0*
#71
b10010000 '
b10010000 ,
b10010000 4
b10010000 6
b10001100 &
b10001100 +
b10001100 .
b10001100 1
b10001100 -
1%
1*
#72
0%
0*
#73
b10010100 '
b10010100 ,
b10010100 4
b10010100 6
b10010000 &
b10010000 +
b10010000 .
b10010000 1
b10010000 -
1%
1*
#74
0%
0*
#75
b10011000 '
b10011000 ,
b10011000 4
b10011000 6
b10010100 &
b10010100 +
b10010100 .
b10010100 1
b10010100 -
1%
1*
#76
0%
0*
#77
b10011100 '
b10011100 ,
b10011100 4
b10011100 6
b10011000 &
b10011000 +
b10011000 .
b10011000 1
b10011000 -
1%
1*
#78
0%
0*
#79
b10100000 '
b10100000 ,
b10100000 4
b10100000 6
b10011100 &
b10011100 +
b10011100 .
b10011100 1
b10011100 -
1%
1*
#80
0%
0*
#81
b10100100 '
b10100100 ,
b10100100 4
b10100100 6
b10100000 &
b10100000 +
b10100000 .
b10100000 1
b10100000 -
1%
1*
#82
0%
0*
#83
b10101000 '
b10101000 ,
b10101000 4
b10101000 6
b10100100 &
b10100100 +
b10100100 .
b10100100 1
b10100100 -
1%
1*
#84
0%
0*
#85
b10101100 '
b10101100 ,
b10101100 4
b10101100 6
b10101000 &
b10101000 +
b10101000 .
b10101000 1
b10101000 -
1%
1*
#86
0%
0*
#87
b10110000 '
b10110000 ,
b10110000 4
b10110000 6
b10101100 &
b10101100 +
b10101100 .
b10101100 1
b10101100 -
1%
1*
#88
0%
0*
#89
b10110100 '
b10110100 ,
b10110100 4
b10110100 6
b10110000 &
b10110000 +
b10110000 .
b10110000 1
b10110000 -
1%
1*
#90
0%
0*
#91
b10111000 '
b10111000 ,
b10111000 4
b10111000 6
b10110100 &
b10110100 +
b10110100 .
b10110100 1
b10110100 -
1%
1*
#92
0%
0*
#93
b10111100 '
b10111100 ,
b10111100 4
b10111100 6
b10111000 &
b10111000 +
b10111000 .
b10111000 1
b10111000 -
1%
1*
#94
0%
0*
#95
b11000000 '
b11000000 ,
b11000000 4
b11000000 6
b10111100 &
b10111100 +
b10111100 .
b10111100 1
b10111100 -
1%
1*
#96
0%
0*
#97
b11000100 '
b11000100 ,
b11000100 4
b11000100 6
b11000000 &
b11000000 +
b11000000 .
b11000000 1
b11000000 -
1%
1*
#98
0%
0*
#99
b11001000 '
b11001000 ,
b11001000 4
b11001000 6
b11000100 &
b11000100 +
b11000100 .
b11000100 1
b11000100 -
1%
1*
#100
0%
0*
#101
b11001100 '
b11001100 ,
b11001100 4
b11001100 6
b11001000 &
b11001000 +
b11001000 .
b11001000 1
b11001000 -
1%
1*
#102
0%
0*
