src/RAM32.v
module RAM32(
  input [31:0] addr, dataIn,
  input clk, writeEnable, enable,
  output [31:0] dataOut
);

  reg [31:0] memory[31:0];

  integer i;

  initial begin
    for (i = 0; i < 31; i = i + 1) begin
      memory[i] = 32'h00000000;
    end
  end

  always @(posedge clk) begin
    if ((writeEnable == 1) && (addr < 31)) begin
      memory[addr] = dataIn;
    end
  end
  
  // We assign 0 to any address that is above 31 because we cannot have actual
  // data that spans to that width of memory 9about 16 GB, cannot simulate)
  // hence we assume its just 0 instead of high impedance
  assign dataOut = ((addr < 31) && (enable == 1)) ? memory[addr] : 32'h00000000;

endmodule

tb/RAM32tb.v
module RAM32tb();

  reg [31:0] addr, dataIn;
  reg clk, writeEnable, RAMWriteEnable, RAMEnable;
  wire [31:0] dataOut;

  RAM32 uut(
    .addr(addr), .dataIn(dataIn),
    .clk(clk), .writeEnable(writeEnable),
    .dataOut(dataOut),.enable(RAMEnable)
  );

  always begin
    #3; clk = ~clk;
  end

  initial begin
  $dumpfile("build/RAM32tb.vcd");
  $dumpvars(0, RAM32tb);

  clk = 0;
  RAMEnable = 0;

  addr = 0; #3;
  RAMEnable = 1;
  #3;
  RAMEnable = 0;

  addr = 5;
  dataIn = 7;
  writeEnable = 1;
  #1;
  writeEnable = 0; #2;

  RAMEnable = 1;
  addr = 5;
  dataIn = 7;
  writeEnable = 1;
  #1;
  writeEnable = 0; #2;
  RAMEnable = 0;


  RAMEnable = 1;
  addr = 3; #3;
  addr = 5; #3;

  $finish;
  end

endmodule

build/RAM32tb.vcd
$date
	Wed Mar  4 21:02:35 2026
$end
$version
	Icarus Verilog
$end
$timescale
	1s
$end
$scope module RAM32tb $end
$var wire 32 ! dataOut [31:0] $end
$var reg 1 " RAMEnable $end
$var reg 32 # addr [31:0] $end
$var reg 1 $ clk $end
$var reg 32 % dataIn [31:0] $end
$var reg 1 & writeEnable $end
$scope module uut $end
$var wire 32 ' addr [31:0] $end
$var wire 1 $ clk $end
$var wire 32 ( dataIn [31:0] $end
$var wire 1 " enable $end
$var wire 1 & writeEnable $end
$var wire 32 ) dataOut [31:0] $end
$var integer 32 * i [31:0] $end
$upscope $end
$upscope $end
$enddefinitions $end
$comment Show the parameter values. $end
$dumpall
$end
#0
$dumpvars
b11111 *
bz )
bx (
b0 '
x&
bx %
0$
b0 #
0"
bz !
$end
#3
b0 !
b0 )
1"
1$
#6
bz !
bz )
1&
b111 %
b111 (
b101 #
b101 '
0"
0$
#7
0&
#9
b111 !
b111 )
1&
1"
1$
#10
0&
#12
b0 !
b0 )
b11 #
b11 '
1"
0$
#15
b111 !
b111 )
b101 #
b101 '
1$
